st_mapbox/__init__.py
st_mapbox/frontend/build/asset-manifest.json
st_mapbox/frontend/build/bootstrap.min.css
st_mapbox/frontend/build/index.html
st_mapbox/frontend/build/precache-manifest.00c2ce0925df3913427e5f1e355cbe90.js
st_mapbox/frontend/build/service-worker.js
st_mapbox/frontend/build/static/js/2.f1188555.chunk.js
st_mapbox/frontend/build/static/js/2.f1188555.chunk.js.LICENSE.txt
st_mapbox/frontend/build/static/js/2.f1188555.chunk.js.map
st_mapbox/frontend/build/static/js/main.af9bd733.chunk.js
st_mapbox/frontend/build/static/js/main.af9bd733.chunk.js.map
st_mapbox/frontend/build/static/js/runtime-main.44d30fc2.js
st_mapbox/frontend/build/static/js/runtime-main.44d30fc2.js.map
streamlit_mapbox-0.0.1.dist-info/LICENSE
streamlit_mapbox-0.0.1.dist-info/METADATA
streamlit_mapbox-0.0.1.dist-info/WHEEL
streamlit_mapbox-0.0.1.dist-info/top_level.txt
streamlit_mapbox-0.0.1.dist-info/RECORD
