Metadata-Version: 2.1
Name: streamlit-mapbox
Version: 0.0.1
Summary: Streamlit component for rendering Mapbox GL JS
Home-page: https://github.com/giswqs/streamlit-mapbox
Author: Qiusheng Wu
Author-email: giswqs@gmail.com
License: UNKNOWN
Platform: UNKNOWN
Classifier: Development Status :: 2 - Pre-Alpha
Classifier: Intended Audience :: Developers
Classifier: License :: OSI Approved :: MIT License
Classifier: Natural Language :: English
Classifier: Programming Language :: Python :: 3
Classifier: Programming Language :: Python :: 3.7
Classifier: Programming Language :: Python :: 3.8
Classifier: Programming Language :: Python :: 3.9
Classifier: Programming Language :: Python :: 3.10
Requires-Python: >=3.7
License-File: LICENSE
Requires-Dist: streamlit (>=0.63)
